bw2_aware/__init__.py
bw2_aware/aware.py
bw2_aware/base.py
bw2_aware/data/aware.gpkg
bw2_aware-0.2.1.dist-info/LICENSE.txt
bw2_aware-0.2.1.dist-info/METADATA
bw2_aware-0.2.1.dist-info/WHEEL
bw2_aware-0.2.1.dist-info/top_level.txt
bw2_aware-0.2.1.dist-info/RECORD
