Metadata-Version: 2.1
Name: bw2-aware
Version: 0.2.1
Summary: AWARE regionalized LCIA method for Brightway2
Home-page: https://github.com/cmutel/bw2_aware
Author: Chris Mutel
Author-email: cmutel@gmail.com
License: Copyright (c) 2018, Chris Mutel and Paul Scherrer Institut
Requires-Dist: brightway2
Requires-Dist: bw2regional
Requires-Dist: wrapt
